hybrid_slug/__init__.py
hybrid_slug/api/__init__.py
hybrid_slug/api/base.py
hybrid_slug/api/exceptions.py
hybrid_slug/api/theoneapi.py
hybrid_slug-0.1.0.dist-info/WHEEL
hybrid_slug-0.1.0.dist-info/METADATA
hybrid_slug-0.1.0.dist-info/RECORD
