Metadata-Version: 2.1
Name: hybrid-slug
Version: 0.1.0
Summary: SDK for The One API
Requires-Python: >=3.9,<4.0
Classifier: Programming Language :: Python :: 3
Classifier: Programming Language :: Python :: 3.9
Requires-Dist: requests (>=2.28.2,<3.0.0)
